[
  {
    "id": null,
    "name": "Evaluación de la luz de los proveedores por ANDOVAR",
    "type": "processTitle"
  },
  {
    "id": 3,
    "name": "Validación del correo electrónico con ANDOVAR",
    "type": null
  },
  {
    "id": 4,
    "name": "Proceso de validación del dominio ANDOVAR",
    "type": null
  },
  {
    "id": 2,
    "name": "Actualización del número DUNS mediante ANDOVAR",
    "type": null
  },
  {
    "id": 5,
    "name": "Obtención de la puntuación D&B con ANDOVAR",
    "type": null
  },
  {
    "id": 6,
    "name": "ANDOVAR Puntuación de riesgo personalizada",
    "type": null
  },
  {
    "id": 7,
    "name": "Revisión de la proyección de luz con ANDOVAR",
    "type": null
  },
  {
    "id": 8,
    "name": "Actualización de la situación de los proveedores ANDOVAR",
    "type": null
  },
  {
    "id": 10,
    "name": "Resultados de la evaluación ESG de proveedores de ANDOVAR",
    "type": null
  },
  {
    "id": 11,
    "name": "Análisis financiero de ANDOVAR",
    "type": null
  },
  {
    "id": 12,
    "name": "Comprobación del cumplimiento de ANDOVAR",
    "type": null
  },
  {
    "id": 13,
    "name": "Integración de los datos de ANDOVAR",
    "type": null
  },
  {
    "id": 14,
    "name": "Evaluación de riesgos de ANDOVAR",
    "type": null
  },
  {
    "id": 15,
    "name": "Verificación de proveedores de ANDOVAR",
    "type": null
  },
  {
    "id": 16,
    "name": "ANDOVAR Detección de fraudes",
    "type": null
  },
  {
    "id": 17,
    "name": "Revisión de los informes de ANDOVAR",
    "type": null
  },
  {
    "id": 18,
    "name": "Informes de cumplimiento de ANDOVAR",
    "type": null
  },
  {
    "id": 19,
    "name": "Generación de información ANDOVAR",
    "type": null
  },
  {
    "id": 20,
    "name": "Incorporación de proveedores a ANDOVAR",
    "type": null
  }
]
